odoo/addons/l10n_br_account_bank_statement_import_cnab/README.rst
odoo/addons/l10n_br_account_bank_statement_import_cnab/__init__.py
odoo/addons/l10n_br_account_bank_statement_import_cnab/__manifest__.py
odoo/addons/l10n_br_account_bank_statement_import_cnab/i18n/l10n_br_account_bank_statement_import_cnab.pot
odoo/addons/l10n_br_account_bank_statement_import_cnab/models/__init__.py
odoo/addons/l10n_br_account_bank_statement_import_cnab/models/account_journal.py
odoo/addons/l10n_br_account_bank_statement_import_cnab/readme/CONFIGURE.rst
odoo/addons/l10n_br_account_bank_statement_import_cnab/readme/CONTRIBUTORS.rst
odoo/addons/l10n_br_account_bank_statement_import_cnab/readme/CREDITS.rst
odoo/addons/l10n_br_account_bank_statement_import_cnab/readme/DESCRIPTION.rst
odoo/addons/l10n_br_account_bank_statement_import_cnab/readme/HISTORY.rst
odoo/addons/l10n_br_account_bank_statement_import_cnab/readme/INSTALL.rst
odoo/addons/l10n_br_account_bank_statement_import_cnab/readme/USAGE.rst
odoo/addons/l10n_br_account_bank_statement_import_cnab/static/description/icon.png
odoo/addons/l10n_br_account_bank_statement_import_cnab/static/description/index.html
odoo/addons/l10n_br_account_bank_statement_import_cnab/tests/__init__.py
odoo/addons/l10n_br_account_bank_statement_import_cnab/tests/test_import_bank_statement.py
odoo/addons/l10n_br_account_bank_statement_import_cnab/tests/test_cnab_file/cnab240segmentoE.txt
odoo/addons/l10n_br_account_bank_statement_import_cnab/views/view_account_bank_statement_import.xml
odoo/addons/l10n_br_account_bank_statement_import_cnab/wizard/__init__.py
odoo/addons/l10n_br_account_bank_statement_import_cnab/wizard/account_bank_statement_import.py
odoo12_addon_l10n_br_account_bank_statement_import_cnab-12.0.1.0.0.99.dev4.dist-info/METADATA
odoo12_addon_l10n_br_account_bank_statement_import_cnab-12.0.1.0.0.99.dev4.dist-info/WHEEL
odoo12_addon_l10n_br_account_bank_statement_import_cnab-12.0.1.0.0.99.dev4.dist-info/top_level.txt
odoo12_addon_l10n_br_account_bank_statement_import_cnab-12.0.1.0.0.99.dev4.dist-info/RECORD
